[
  {"npi":"1234567001","totalPrescriptions":245,"opioidPrescriptions":12,"antibioticPrescriptions":89,"totalBeneficiaries":1820,"averageBeneficiaryAge":52.3,"femaleBeneficiaryPct":58.2,"dualEligiblePct":14.5,"averageRiskScore":1.12,"totalMedicarePayments":142000,"graduationYear":2003,"medicalSchool":"Arizona School of Dentistry","source":"cms-fixture"},
  {"npi":"1234567002","totalPrescriptions":198,"opioidPrescriptions":8,"antibioticPrescriptions":76,"totalBeneficiaries":1540,"averageBeneficiaryAge":48.7,"femaleBeneficiaryPct":61.0,"dualEligiblePct":11.2,"averageRiskScore":1.05,"totalMedicarePayments":118000,"graduationYear":2008,"medicalSchool":"Midwestern University CDM","source":"cms-fixture"},
  {"npi":"1234567003","totalPrescriptions":312,"opioidPrescriptions":3,"antibioticPrescriptions":120,"totalBeneficiaries":2100,"averageBeneficiaryAge":9.5,"femaleBeneficiaryPct":49.0,"dualEligiblePct":18.3,"averageRiskScore":0.88,"totalMedicarePayments":95000,"graduationYear":2006,"medicalSchool":"University of the Pacific","source":"cms-fixture"},
  {"npi":"1234567005","totalPrescriptions":420,"opioidPrescriptions":85,"antibioticPrescriptions":145,"totalBeneficiaries":980,"averageBeneficiaryAge":44.2,"femaleBeneficiaryPct":55.0,"dualEligiblePct":12.0,"averageRiskScore":1.35,"totalMedicarePayments":285000,"graduationYear":2001,"medicalSchool":"Harvard School of Dental Medicine","source":"cms-fixture"},
  {"npi":"1234567007","totalPrescriptions":180,"opioidPrescriptions":15,"antibioticPrescriptions":68,"totalBeneficiaries":890,"averageBeneficiaryAge":50.1,"femaleBeneficiaryPct":57.5,"dualEligiblePct":9.8,"averageRiskScore":1.08,"totalMedicarePayments":105000,"graduationYear":2005,"medicalSchool":"University of Michigan","source":"cms-fixture"},
  {"npi":"1234567009","totalPrescriptions":210,"opioidPrescriptions":10,"antibioticPrescriptions":82,"totalBeneficiaries":1650,"averageBeneficiaryAge":51.8,"femaleBeneficiaryPct":59.3,"dualEligiblePct":16.0,"averageRiskScore":1.15,"totalMedicarePayments":130000,"graduationYear":2007,"medicalSchool":"UCSF School of Dentistry","source":"cms-fixture"},
  {"npi":"1234567011","totalPrescriptions":275,"opioidPrescriptions":14,"antibioticPrescriptions":105,"totalBeneficiaries":2050,"averageBeneficiaryAge":53.6,"femaleBeneficiaryPct":56.8,"dualEligiblePct":19.5,"averageRiskScore":1.22,"totalMedicarePayments":165000,"graduationYear":2004,"medicalSchool":"UT Health San Antonio","source":"cms-fixture"},
  {"npi":"1234567014","totalPrescriptions":95,"opioidPrescriptions":2,"antibioticPrescriptions":35,"totalBeneficiaries":720,"averageBeneficiaryAge":14.2,"femaleBeneficiaryPct":52.0,"dualEligiblePct":8.5,"averageRiskScore":0.78,"totalMedicarePayments":62000,"graduationYear":2014,"medicalSchool":"Baylor College of Dentistry","source":"cms-fixture"},
  {"npi":"1234567017","totalPrescriptions":380,"opioidPrescriptions":72,"antibioticPrescriptions":130,"totalBeneficiaries":850,"averageBeneficiaryAge":46.5,"femaleBeneficiaryPct":54.0,"dualEligiblePct":10.2,"averageRiskScore":1.30,"totalMedicarePayments":260000,"graduationYear":2005,"medicalSchool":"UCLA School of Dentistry","source":"cms-fixture"},
  {"npi":"1234567020","totalPrescriptions":230,"opioidPrescriptions":11,"antibioticPrescriptions":90,"totalBeneficiaries":1780,"averageBeneficiaryAge":50.5,"femaleBeneficiaryPct":60.2,"dualEligiblePct":13.8,"averageRiskScore":1.10,"totalMedicarePayments":138000,"graduationYear":2010,"medicalSchool":"University of the Pacific","source":"cms-fixture"},
  {"npi":"1234567022","totalPrescriptions":205,"opioidPrescriptions":9,"antibioticPrescriptions":78,"totalBeneficiaries":1580,"averageBeneficiaryAge":49.3,"femaleBeneficiaryPct":62.5,"dualEligiblePct":15.0,"averageRiskScore":1.07,"totalMedicarePayments":122000,"graduationYear":2012,"medicalSchool":"University of Illinois Chicago","source":"cms-fixture"},
  {"npi":"1234567025","totalPrescriptions":88,"opioidPrescriptions":1,"antibioticPrescriptions":32,"totalBeneficiaries":680,"averageBeneficiaryAge":13.8,"femaleBeneficiaryPct":51.5,"dualEligiblePct":7.2,"averageRiskScore":0.75,"totalMedicarePayments":55000,"graduationYear":2003,"medicalSchool":"Northwestern University","source":"cms-fixture"},
  {"npi":"1234567027","totalPrescriptions":240,"opioidPrescriptions":13,"antibioticPrescriptions":95,"totalBeneficiaries":1720,"averageBeneficiaryAge":52.0,"femaleBeneficiaryPct":58.8,"dualEligiblePct":17.5,"averageRiskScore":1.18,"totalMedicarePayments":145000,"graduationYear":2008,"medicalSchool":"Medical College of Georgia","source":"cms-fixture"},
  {"npi":"1234567030","totalPrescriptions":190,"opioidPrescriptions":7,"antibioticPrescriptions":72,"totalBeneficiaries":1450,"averageBeneficiaryAge":47.8,"femaleBeneficiaryPct":60.0,"dualEligiblePct":12.5,"averageRiskScore":1.02,"totalMedicarePayments":112000,"graduationYear":2009,"medicalSchool":"Tufts University","source":"cms-fixture"}
]
